setup.py
cratis_admin_suit/__init__.py
cratis_admin_suit/features.py
django_cratis_admin_suit.egg-info/PKG-INFO
django_cratis_admin_suit.egg-info/SOURCES.txt
django_cratis_admin_suit.egg-info/dependency_links.txt
django_cratis_admin_suit.egg-info/requires.txt
django_cratis_admin_suit.egg-info/top_level.txt