Metadata-Version: 1.0
Name: django-cratis-admin-suit
Version: 0.1.0
Summary: Integrates django-suit theme to django-admin
Home-page: UNKNOWN
Author: Alex Rudakov
Author-email: ribozz@gmail.com
License: MIT
Platform: UNKNOWN
